README.rst
setup.py
mongomotormodel/__init__.py
mongomotormodel/model.py
mongomotormodel/validators.py
mongomotormodel.egg-info/PKG-INFO
mongomotormodel.egg-info/SOURCES.txt
mongomotormodel.egg-info/dependency_links.txt
mongomotormodel.egg-info/not-zip-safe
mongomotormodel.egg-info/requires.txt
mongomotormodel.egg-info/top_level.txt